topsis/__init__.py
topsis/__main__.py
Topsis_Sahajdeep_101916085-1.0.1.dist-info/LICENSE
Topsis_Sahajdeep_101916085-1.0.1.dist-info/METADATA
Topsis_Sahajdeep_101916085-1.0.1.dist-info/WHEEL
Topsis_Sahajdeep_101916085-1.0.1.dist-info/entry_points.txt
Topsis_Sahajdeep_101916085-1.0.1.dist-info/top_level.txt
Topsis_Sahajdeep_101916085-1.0.1.dist-info/RECORD
