Metadata-Version: 2.1
Name: Topsis-Sahajdeep-101916085
Version: 1.0.1
Summary: TOPSIS method for multiple-criteria decision making (MCDM).
Author: Sahajdeep Singh Kharbanda
Author-email: kharbandasahajsingh@gmail.com
License: SELF
Platform: UNKNOWN
Classifier: Programming Language :: Python :: 3.9
License-File: LICENSE
Requires-Dist: pandas
Requires-Dist: numpy
